pyCryptoPayAPI/__init__.py
pyCryptoPayAPI/api.py
pyCryptoPayAPI/classes.py
pyCryptoPayAPI/tests.py
pyCryptoPayAPI/version.py
pycryptopayapi-1.0.2.dist-info/METADATA
pycryptopayapi-1.0.2.dist-info/WHEEL
pycryptopayapi-1.0.2.dist-info/licenses/LICENSE
pycryptopayapi-1.0.2.dist-info/RECORD
