Metadata-Version: 2.4
Name: pyCryptoPayAPI
Version: 1.0.2
Summary: Simple Python implementation of Crypto Pay API (Crypto Pay is a payment system based on @CryptoBot).
Project-URL: Homepage, https://github.com/Badiboy/pyCryptoPayAPI
Project-URL: Documentation, https://github.com/Badiboy/pyCryptoPayAPI
Project-URL: Repository, https://github.com/Badiboy/pyCryptoPayAPI
Project-URL: Issues, https://github.com/Badiboy/pyCryptoPayAPI/issues
Author: Badiboy
License: MIT license
License-File: LICENSE
Keywords: api,crypto,crypto-payment,cryptobot,cryptopay,python
Classifier: Development Status :: 5 - Production/Stable
Classifier: Environment :: Console
Classifier: License :: OSI Approved :: MIT License
Classifier: Programming Language :: Python :: 3
Classifier: Programming Language :: Python :: 3.9
Classifier: Programming Language :: Python :: 3.10
Classifier: Programming Language :: Python :: 3.11
Classifier: Programming Language :: Python :: 3.12
Requires-Python: >=3.9
Requires-Dist: requests
